gprofiler/__init__.py
gprofiler-1.2.2.dist-info/METADATA
gprofiler-1.2.2.dist-info/WHEEL
gprofiler-1.2.2.dist-info/top_level.txt
gprofiler-1.2.2.dist-info/RECORD
